pyrogue/__init__.py
pyrogue/color.py
pyrogue/death_functions.py
pyrogue/engine.py
pyrogue/game_messages.py
pyrogue/game_states.py
pyrogue/input_handlers.py
pyrogue/renderer.py
pyrogue/terminal.py
pyrogue/utilities.py
pyrogue/components/__init__.py
pyrogue/components/ai.py
pyrogue/components/fighter.py
pyrogue/components/fov.py
pyrogue/components/levelable.py
pyrogue/components/player_class.py
pyrogue/entity/__init__.py
pyrogue/entity/entity.py
pyrogue/gamemap/__init__.py
pyrogue/gamemap/gamemap.py
pyrogue-0.0.2.dist-info/LICENSE
pyrogue-0.0.2.dist-info/METADATA
pyrogue-0.0.2.dist-info/WHEEL
pyrogue-0.0.2.dist-info/top_level.txt
pyrogue-0.0.2.dist-info/RECORD
